{"cameraMode":{"drawMode":0,"name":"Shaded","section":"Shading Mode"},"sceneLighting":true,"audioPlay":false,"sceneViewState":{"m_AlwaysRefresh":false,"showFog":true,"showSkybox":true,"showFlares":true,"showImageEffects":true,"showParticleSystems":true,"showVisualEffectGraphs":true,"m_FxEnabled":true},"in2DMode":false,"pivot":{"x":0.4191669225692749,"y":-0.9461003541946411,"z":6.065201282501221},"rotation":{"x":0.1196691170334816,"y":0.028278211131691934,"z":-0.003382822498679161,"w":0.9924390912055969},"size":5.798102378845215,"orthographic":false}